bluezero/GATT.py
bluezero/__init__.py
bluezero/adapter.py
bluezero/advertisement.py
bluezero/async_tools.py
bluezero/broadcaster.py
bluezero/central.py
bluezero/constants.py
bluezero/dbus_tools.py
bluezero/device.py
bluezero/eddystone_beacon.py
bluezero/localGATT.py
bluezero/media_player.py
bluezero/microbit.py
bluezero/observer.py
bluezero/peripheral.py
bluezero/tools.py
bluezero-0.9.1.dist-info/licenses/LICENSE
bluezero-0.9.1.dist-info/METADATA
bluezero-0.9.1.dist-info/WHEEL
bluezero-0.9.1.dist-info/top_level.txt
bluezero-0.9.1.dist-info/RECORD
