Metadata-Version: 2.4
Name: bluezero
Version: 0.9.1
Summary: Python library for Bluetooth Low Energy (BLE) on Linux
Home-page: https://github.com/ukBaz/python-bluezero
Author: Barry Byford
Author-email: barry_byford@yahoo.co.uk
Maintainer: Barry Byford
Maintainer-email: barry_byford@yahoo.co.uk
License: MIT
Keywords: Bluetooth BLE development
Classifier: Development Status :: 4 - Beta
Classifier: Intended Audience :: Developers
Classifier: Intended Audience :: Education
Classifier: Topic :: System :: Hardware
Classifier: Topic :: Software Development :: Embedded Systems
Classifier: Topic :: Home Automation
Classifier: Topic :: Education
Classifier: License :: OSI Approved :: MIT License
Classifier: Programming Language :: Python :: 3 :: Only
License-File: LICENSE
Requires-Dist: PyGObject<3.52.0
Provides-Extra: rel
Requires-Dist: bumpversion; extra == "rel"
Requires-Dist: twine; extra == "rel"
Provides-Extra: docs
Requires-Dist: sphinx; extra == "docs"
Requires-Dist: sphinx_rtd_theme; extra == "docs"
Provides-Extra: test
Requires-Dist: coverage; extra == "test"
Requires-Dist: pycodestyle; extra == "test"
Requires-Dist: python-dbusmock; extra == "test"
Provides-Extra: dev
Requires-Dist: bumpversion; extra == "dev"
Requires-Dist: twine; extra == "dev"
Requires-Dist: sphinx; extra == "dev"
Requires-Dist: sphinx_rtd_theme; extra == "dev"
Requires-Dist: coverage; extra == "dev"
Requires-Dist: pycodestyle; extra == "dev"
Requires-Dist: python-dbusmock; extra == "dev"
Dynamic: author
Dynamic: author-email
Dynamic: classifier
Dynamic: description
Dynamic: description-content-type
Dynamic: home-page
Dynamic: keywords
Dynamic: license
Dynamic: license-file
Dynamic: maintainer
Dynamic: maintainer-email
Dynamic: provides-extra
Dynamic: requires-dist
Dynamic: summary
